inovai/__init__.py
inovai/dtos.py
inovai/entities.py
inovai/enums.py
inovai/log.py
inovai/models/Endereco.py
inovai/models/NFe.py
inovai/models/NFeBoleto.py
inovai/models/NFeCartao.py
inovai/models/NFeDadosAtivos.py
inovai/models/NFeDetalhePagamento.py
inovai/models/NFeDocImportacao.py
inovai/models/NFeDocImportacaoAdicao.py
inovai/models/NFeDocRef.py
inovai/models/NFeDuplicata.py
inovai/models/NFeEnvioXML.py
inovai/models/NFeEnvolvido.py
inovai/models/NFeExportacao.py
inovai/models/NFeFatura.py
inovai/models/NFeImposto.py
inovai/models/NFeImpostoRetido.py
inovai/models/NFeIntermediadorTransacao.py
inovai/models/NFeItem.py
inovai/models/NFeItemDadosCombustivel.py
inovai/models/NFeItemExportacao.py
inovai/models/NFeItemOrigemCombustivel.py
inovai/models/NFeObservacao.py
inovai/models/NFeObservacaoItem.py
inovai/models/NFeOrigem.py
inovai/models/NFePagamento.py
inovai/models/NFeProcReferenciado.py
inovai/models/NFeTransporte.py
inovai/models/NFeVeiculo.py
inovai/models/NFeVolume.py
inovai/models/__init__.py
inovai/utils/__init__.py
inovai/utils/util.py
ipiranga_inovai_project_lib-6.5.dist-info/LICENSE
ipiranga_inovai_project_lib-6.5.dist-info/METADATA
ipiranga_inovai_project_lib-6.5.dist-info/WHEEL
ipiranga_inovai_project_lib-6.5.dist-info/top_level.txt
ipiranga_inovai_project_lib-6.5.dist-info/RECORD
