Metadata-Version: 2.1
Name: ipiranga-inovai-project-lib
Version: 6.5
Summary: Projeto criado para importação genérica de entidades
Home-page: https://gitlab.ipirangacloud.com/clayton.monteiro.ext/ipiranga-inovai-project-lib
Author: Clayton Sandes Monteiro
Author-email: clayton.monteiro.ext@ipiranga.ipiranga
License: MIT
Keywords: inovai
Classifier: Programming Language :: Python :: 3
Classifier: License :: OSI Approved :: MIT License
License-File: LICENSE
